DecisionTree/__init__.py
DecisionTree/src/DecisionTree.py
DecisionTree/src/__init__.py
DecisionTree/src/helpers.py
DecisionTree/test/Full_test.py
DecisionTree/test/Testing.py
DecisionTree/test/__init__.py
DecisionTreeClassifier-0.0.7.dist-info/LICENCE.txt
DecisionTreeClassifier-0.0.7.dist-info/METADATA
DecisionTreeClassifier-0.0.7.dist-info/WHEEL
DecisionTreeClassifier-0.0.7.dist-info/top_level.txt
DecisionTreeClassifier-0.0.7.dist-info/RECORD
