Metadata-Version: 2.1
Name: DecisionTreeClassifier
Version: 0.0.7
Summary: A Decision Tree Classifier.
Home-page: https://github.com/mlouii/Decision-Tree-Practicum
Author: Mark Lou, Jobin Joyson
Author-email: mlou@hawk.iit.edu, jjoyson1@hawk.iit.edu
License: MIT
Keywords: decision tree
Classifier: Intended Audience :: Education
Classifier: License :: OSI Approved :: MIT License
Classifier: Programming Language :: Python :: 3
License-File: LICENCE.txt
Requires-Dist: numpy
Requires-Dist: pandas
